mlmagic/__init__.py
mlmagic/demo.py
mlmagic/analyze/__init__.py
mlmagic/analyze/categorical.py
mlmagic/analyze/missing.py
mlmagic/analyze/na_values.py
mlmagic/analyze/numeric.py
mlmagic_pkg/__init__.py
mlmagic_pkg/demo.py
mlmagic-0.1.6.dist-info/LICENSE
mlmagic-0.1.6.dist-info/METADATA
mlmagic-0.1.6.dist-info/WHEEL
mlmagic-0.1.6.dist-info/top_level.txt
mlmagic-0.1.6.dist-info/RECORD
