Metadata-Version: 2.1
Name: mlmagic
Version: 0.1.6
Summary: A ML supportive library for analysis
Home-page: https://github.com/bwvdhelm/mlmagic
Author: Bob van der Helm
Author-email: bvanderh@gmail.com
License: UNKNOWN
Platform: UNKNOWN
Classifier: Programming Language :: Python :: 3
Classifier: License :: OSI Approved
Classifier: Operating System :: OS Independent
